MANIFEST.in
README.txt
setup.py
.tx/config
docs/HISTORY.txt
docs/INSTALL.txt
docs/LICENSE.GPL
docs/LICENSE.txt
quintagroup/__init__.py
quintagroup.captcha.core.egg-info/PKG-INFO
quintagroup.captcha.core.egg-info/SOURCES.txt
quintagroup.captcha.core.egg-info/dependency_links.txt
quintagroup.captcha.core.egg-info/entry_points.txt
quintagroup.captcha.core.egg-info/namespace_packages.txt
quintagroup.captcha.core.egg-info/not-zip-safe
quintagroup.captcha.core.egg-info/requires.txt
quintagroup.captcha.core.egg-info/top_level.txt
quintagroup/captcha/__init__.py
quintagroup/captcha/core/CaptchaTool.py
quintagroup/captcha/core/Crypto.py
quintagroup/captcha/core/__init__.py
quintagroup/captcha/core/config.py
quintagroup/captcha/core/configure.zcml
quintagroup/captcha/core/encrypt_images.py
quintagroup/captcha/core/setuphandlers.py
quintagroup/captcha/core/utils.py
quintagroup/captcha/core/Extensions/Install.py
quintagroup/captcha/core/Extensions/__init__.py
quintagroup/captcha/core/data/__init__.py
quintagroup/captcha/core/data/basic_english.py
quintagroup/captcha/core/data/fonts/vera/Vera.ttf
quintagroup/captcha/core/data/fonts/vera/VeraBI.ttf
quintagroup/captcha/core/data/fonts/vera/VeraBd.ttf
quintagroup/captcha/core/data/fonts/vera/VeraIt.ttf
quintagroup/captcha/core/data/fonts/vera/VeraMoBI.ttf
quintagroup/captcha/core/data/fonts/vera/VeraMoBd.ttf
quintagroup/captcha/core/data/fonts/vera/VeraMoIt.ttf
quintagroup/captcha/core/data/fonts/vera/VeraMono.ttf
quintagroup/captcha/core/data/fonts/vera/VeraSe.ttf
quintagroup/captcha/core/data/fonts/vera/VeraSeBd.ttf
quintagroup/captcha/core/locales/quintagroup.captcha.core.pot
quintagroup/captcha/core/locales/cs/LC_MESSAGES/quintagroup.captcha.core.po
quintagroup/captcha/core/locales/da/LC_MESSAGES/quintagroup.captcha.core.po
quintagroup/captcha/core/locales/de/LC_MESSAGES/quintagroup.captcha.core.po
quintagroup/captcha/core/locales/en/LC_MESSAGES/quintagroup.captcha.core.po
quintagroup/captcha/core/locales/es/LC_MESSAGES/quintagroup.captcha.core.po
quintagroup/captcha/core/locales/fr/LC_MESSAGES/quintagroup.captcha.core.po
quintagroup/captcha/core/locales/it/LC_MESSAGES/quintagroup.captcha.core.po
quintagroup/captcha/core/locales/ja/LC_MESSAGES/quintagroup.captcha.core.po
quintagroup/captcha/core/locales/pl/LC_MESSAGES/quintagroup.captcha.core.po
